{
  "id": "f5ab48ec-149a-435e-b591-a160101a2875",
  "prevId": "00000000-0000-0000-0000-000000000000",
  "version": "7",
  "dialect": "postgresql",
  "tables": {
    "public.doors": {
      "name": "doors",
      "schema": "",
      "columns": {
        "id": {
          "name": "id",
          "type": "uuid",
          "primaryKey": true,
          "notNull": true,
          "default": "gen_random_uuid()"
        },
        "title": {
          "name": "title",
          "type": "text",
          "primaryKey": false,
          "notNull": true
        },
        "description": {
          "name": "description",
          "type": "text",
          "primaryKey": false,
          "notNull": false
        },
        "cleanliness": {
          "name": "cleanliness",
          "type": "cleanliness",
          "typeSchema": "public",
          "primaryKey": false,
          "notNull": true
        },
        "image_url": {
          "name": "image_url",
          "type": "text",
          "primaryKey": false,
          "notNull": false
        },
        "latitude": {
          "name": "latitude",
          "type": "double precision",
          "primaryKey": false,
          "notNull": true
        },
        "longitude": {
          "name": "longitude",
          "type": "double precision",
          "primaryKey": false,
          "notNull": true
        }
      },
      "indexes": {
        "doors_location_idx": {
          "name": "doors_location_idx",
          "columns": [
            {
              "expression": "latitude",
              "isExpression": false,
              "asc": true,
              "nulls": "last"
            },
            {
              "expression": "longitude",
              "isExpression": false,
              "asc": true,
              "nulls": "last"
            }
          ],
          "isUnique": false,
          "concurrently": false,
          "method": "btree",
          "with": {}
        }
      },
      "foreignKeys": {},
      "compositePrimaryKeys": {},
      "uniqueConstraints": {},
      "policies": {},
      "checkConstraints": {},
      "isRLSEnabled": false
    }
  },
  "enums": {
    "public.cleanliness": {
      "name": "cleanliness",
      "schema": "public",
      "values": [
        "horrifying",
        "dirty",
        "smudged up",
        "decent",
        "immaculate"
      ]
    }
  },
  "schemas": {},
  "sequences": {},
  "roles": {},
  "policies": {},
  "views": {},
  "_meta": {
    "columns": {},
    "schemas": {},
    "tables": {}
  }
}